tests/__init__.py
xntool/__init__.py
xntool/__main__.py
xntool/config.py
xntool/gexcel.py
xntool/gjavabean.py
xntool/love.py
xntool/md5.py
xntool/tail.py
xntool/xfileinput.py
xntool/xqiniu.py
xntool/commands/__init__.py
xntool-0.8.2.data/data/etc/xntool/xntool.conf
xntool-0.8.2.dist-info/DESCRIPTION.rst
xntool-0.8.2.dist-info/METADATA
xntool-0.8.2.dist-info/RECORD
xntool-0.8.2.dist-info/WHEEL
xntool-0.8.2.dist-info/entry_points.txt
xntool-0.8.2.dist-info/metadata.json
xntool-0.8.2.dist-info/top_level.txt
