Metadata-Version: 2.0
Name: xntool
Version: 0.8.2
Summary: funny tools
Home-page: https://github.com/yidao620c/xntool
Author: Xiong Neng
Author-email: yidao620@gmail.com
License: MIT
Keywords: xntool,qiuniu,excel,pdf,mysql
Platform: UNKNOWN
Classifier: Development Status :: 4 - Beta
Classifier: Intended Audience :: Developers
Classifier: Topic :: Software Development :: Build Tools
Classifier: License :: OSI Approved :: MIT License
Classifier: Operating System :: MacOS :: MacOS X
Classifier: Operating System :: POSIX
Classifier: Operating System :: POSIX :: BSD
Classifier: Operating System :: POSIX :: Linux
Classifier: Operating System :: Microsoft :: Windows
Classifier: Programming Language :: Python
Classifier: Programming Language :: Python :: 2
Classifier: Programming Language :: Python :: 2.7
Classifier: Programming Language :: Python :: 3
Classifier: Programming Language :: Python :: 3.3
Classifier: Programming Language :: Python :: 3.4
Classifier: Programming Language :: Python :: 3.5
Classifier: Programming Language :: Python :: Implementation :: CPython
Classifier: Programming Language :: Python :: Implementation :: PyPy
Requires-Dist: lxml (>=3.7.2)
Requires-Dist: openpyxl (>=2.4.2)
Requires-Dist: qiniu (>=7.1.1)
Requires-Dist: requests (>=2.6.0)
